seasnake/__init__.py
seasnake/auth.py
seasnake/base.py
seasnake/io.py
seasnake/projects.py
seasnake/summaries/__init__.py
seasnake/summaries/base.py
seasnake/summaries/benthic_lit.py
seasnake/summaries/benthic_photo_quadrat.py
seasnake/summaries/benthic_pit.py
seasnake/summaries/bleaching.py
seasnake/summaries/fish_belt.py
seasnake/summaries/habitat_complexity.py
seasnake/summaries/sample_event.py
seasnake/timer.py
py_seasnake-0.3.3.dist-info/LICENSE
py_seasnake-0.3.3.dist-info/METADATA
py_seasnake-0.3.3.dist-info/WHEEL
py_seasnake-0.3.3.dist-info/RECORD
